{
  "name": "KillerAgencyIDInteractable",
  "fileType": "InteractablePreset",
  "copyFrom": "REF:InteractablePreset|WorkID",
  "presetName": "KillerAgencyIDInteractable",
  "spawnEvidence": "REF:EvidencePreset|KillerAgencyIDEvidence",
  "summaryMessageSource": "a15e007b-b395-462a-8abc-9981c7618564",
  "subObjectClasses": [
    "REF:SubObjectClassPreset|DrawerItemGeneric",
    "REF:SubObjectClassPreset|TabletopItemGeneric"
  ],
  "backupClasses": [
    "REF:SubObjectClassPreset|Junk",
    "REF:SubObjectClassPreset|JunkFloor"
  ],
  "attemptToStoreInFolder": null,
  "folderPlacementChance": 0.5,
  "useSubSpawning": 1,
  "fingerprintsEnabled": true,
  "fingerprintDensity": 3,
  "enableDynamicFingerprints": true,
  "inventoryCarryItem": 1,
  "putDownAtHome": 1,
  "takeWith": 1,
  "putDownPositions": [
    "REF:SubObjectClassPreset|TabletopItemGeneric",
    "REF:SubObjectClassPreset|CountertopItemKitchen"
  ],
  "dontSaveWithSaveGames": false,
  "onlySaveWithSaveGamesIfWorldObject": false
}